zodchy_rabbitmq/__init__.py
zodchy_rabbitmq/consumers/__init__.py
zodchy_rabbitmq/consumers/topic.py
zodchy_rabbitmq/dispatchers/__init__.py
zodchy_rabbitmq/dispatchers/general.py
zodchy_rabbitmq/dispatchers/topic.py
zodchy_rabbitmq/internals/__init__.py
zodchy_rabbitmq/internals/encoders.py
zodchy_rabbitmq-0.1.1.dist-info/METADATA
zodchy_rabbitmq-0.1.1.dist-info/WHEEL
zodchy_rabbitmq-0.1.1.dist-info/RECORD
