Metadata-Version: 2.1
Name: zodchy-rabbitmq
Version: 0.1.1
Summary: RabbitMQ pattern for zodchy architecture
Home-page: https://github.com/smairon/zodchy-rabbitmq
Author: Smairon
Author-email: man@smairon.ru
Requires-Python: >=3.11,<4.0
Classifier: Programming Language :: Python :: 3
Classifier: Programming Language :: Python :: 3.11
Classifier: Programming Language :: Python :: 3.12
Requires-Dist: aio-pika (>=9.5,<10.0)
Requires-Dist: zodchy (>=0,<1)
Project-URL: Repository, https://github.com/smairon/zodchy-rabbitmq
